Workbook

Sheet Simulador
B2: SIMULADOR DE ANTECIPAÇÃO DE RECEBÍVEIS
B3: Painel interativo para projeção de taxas e valor líquido por parcela
B5: PARÂMETROS DA OPERAÇÃO | E5: VALOR BRUTO TOTAL | G5: TOTAL DE DESCONTOS | I5: VALOR LÍQUIDO A RECEBER
B6: Data da Venda | C6: 46315 | E6: =C10 -> 658 | G6: =SUMPRODUCT((Detalhado!A4:A21<=C11)*(Detalhado!J4:J21 + Detalhado!M4:M21)) -> 34.68 | I6: =SUMPRODUCT((Detalhado!A4:A21<=C11)*(Detalhado!N4:N21)) -> 623.32
B7: Data de Recebimento | C7: 46316 | E7: =C11 & " parcelas de " & TEXT(Detalhado!F32, "R$ #,##0.00") -> 2 parcelas de R$ 329,00 | G7: =IF(C10>0, "MDR: " & TEXT(SUMPRODUCT((Detalhado!A4:A21<=C11)*(Detalhado!J4:J21)), "R$ #,##0.00") & " | Antec: " & TEXT(SUMPRODUCT((Detalhado!A4:A21<=C11)*(Detalhado!M4:M21)), "R$ #,##0.00"), "") -> MDR: R$ 14,41 | Antec: R$ 20,27 | I7: =IF(C10>0, "Recebimento líq. de " & ROUND((I6/C10)*100, 2) & "% do total", "") -> Recebimento líq. de 94,73% do total
B8: Taxa Antecipação (mês) | C8: 0.021
B9: Taxa Bandeira (MDR) | C9: 0.0219 | E9: VALOR DAS PARCELAS | G9: CUSTO EFETIVO TOTAL | I9: DATA RECEBIMENTO
B10: Valor Total da Venda | C10: 658 | E10: ="1ª " & TEXT(Detalhado!F31, "R$ #,##0.00") & " | Demais " & TEXT(Detalhado!F32, "R$ #,##0.00") -> 1ª R$ 329,00 | Demais R$ 329,00 | G10: =IF(C10>0, ROUND((G6/C10)*100, 2) & "%", "0.00%") -> 5,27% | I10: =C7 -> 46316
B11: Quantidade de Parcelas | C11: 2 | E11: 1ª parcela ajustada aos centavos | G11: ="Taxa MDR: " & TEXT(C9, "0.00%") & " | Antecipação: " & TEXT(C8, "0.00%") -> Taxa MDR: 2,19% | Antecipação: 2,10% | I11: Liquidação antecipada integral em D+1
B13: DETALHAMENTO DO CRONOGRAMA DE PARCELAS
B14: Parcela | C14: Vencimento Original | D14: Data Recebimento | E14: Dias Antec. | F14: Taxa Antec. | G14: Valor Bruto | H14: Desconto MDR | I14: Desconto Antec. | J14: Valor Líquido
B15: =IF(Detalhado!A4<=$C$11, Detalhado!A4, "") -> 1 | C15: =IF(Detalhado!A4<=$C$11, Detalhado!C4, "") -> 46345 | D15: =IF(Detalhado!A4<=$C$11, Detalhado!D4, "") -> 46316 | E15: =IF(Detalhado!A4<=$C$11, Detalhado!E4, "") -> 29 | F15: =IF(Detalhado!A4<=$C$11, Detalhado!G4, "") -> 0.0203 | G15: =IF(Detalhado!A4<=$C$11, Detalhado!H4, "") -> 329 | H15: =IF(Detalhado!A4<=$C$11, Detalhado!J4, "") -> 7.21 | I15: =IF(Detalhado!A4<=$C$11, Detalhado!M4, "") -> 6.53 | J15: =IF(Detalhado!A4<=$C$11, Detalhado!N4, "") -> 315.26
B16: =IF(Detalhado!A5<=$C$11, Detalhado!A5, "") -> 2 | C16: =IF(Detalhado!A5<=$C$11, Detalhado!C5, "") -> 46377 | D16: =IF(Detalhado!A5<=$C$11, Detalhado!D5, "") -> 46316 | E16: =IF(Detalhado!A5<=$C$11, Detalhado!E5, "") -> 61 | F16: =IF(Detalhado!A5<=$C$11, Detalhado!G5, "") -> 0.0427 | G16: =IF(Detalhado!A5<=$C$11, Detalhado!H5, "") -> 329 | H16: =IF(Detalhado!A5<=$C$11, Detalhado!J5, "") -> 7.2 | I16: =IF(Detalhado!A5<=$C$11, Detalhado!M5, "") -> 13.74 | J16: =IF(Detalhado!A5<=$C$11, Detalhado!N5, "") -> 308.06
B17: =IF(Detalhado!A6<=$C$11, Detalhado!A6, "") | C17: =IF(Detalhado!A6<=$C$11, Detalhado!C6, "") | D17: =IF(Detalhado!A6<=$C$11, Detalhado!D6, "") | E17: =IF(Detalhado!A6<=$C$11, Detalhado!E6, "") | F17: =IF(Detalhado!A6<=$C$11, Detalhado!G6, "") | G17: =IF(Detalhado!A6<=$C$11, Detalhado!H6, "") | H17: =IF(Detalhado!A6<=$C$11, Detalhado!J6, "") | I17: =IF(Detalhado!A6<=$C$11, Detalhado!M6, "") | J17: =IF(Detalhado!A6<=$C$11, Detalhado!N6, "")
B18: =IF(Detalhado!A7<=$C$11, Detalhado!A7, "") | C18: =IF(Detalhado!A7<=$C$11, Detalhado!C7, "") | D18: =IF(Detalhado!A7<=$C$11, Detalhado!D7, "") | E18: =IF(Detalhado!A7<=$C$11, Detalhado!E7, "") | F18: =IF(Detalhado!A7<=$C$11, Detalhado!G7, "") | G18: =IF(Detalhado!A7<=$C$11, Detalhado!H7, "") | H18: =IF(Detalhado!A7<=$C$11, Detalhado!J7, "") | I18: =IF(Detalhado!A7<=$C$11, Detalhado!M7, "") | J18: =IF(Detalhado!A7<=$C$11, Detalhado!N7, "")
B19: =IF(Detalhado!A8<=$C$11, Detalhado!A8, "") | C19: =IF(Detalhado!A8<=$C$11, Detalhado!C8, "") | D19: =IF(Detalhado!A8<=$C$11, Detalhado!D8, "") | E19: =IF(Detalhado!A8<=$C$11, Detalhado!E8, "") | F19: =IF(Detalhado!A8<=$C$11, Detalhado!G8, "") | G19: =IF(Detalhado!A8<=$C$11, Detalhado!H8, "") | H19: =IF(Detalhado!A8<=$C$11, Detalhado!J8, "") | I19: =IF(Detalhado!A8<=$C$11, Detalhado!M8, "") | J19: =IF(Detalhado!A8<=$C$11, Detalhado!N8, "")
B20: =IF(Detalhado!A9<=$C$11, Detalhado!A9, "") | C20: =IF(Detalhado!A9<=$C$11, Detalhado!C9, "") | D20: =IF(Detalhado!A9<=$C$11, Detalhado!D9, "") | E20: =IF(Detalhado!A9<=$C$11, Detalhado!E9, "") | F20: =IF(Detalhado!A9<=$C$11, Detalhado!G9, "") | G20: =IF(Detalhado!A9<=$C$11, Detalhado!H9, "") | H20: =IF(Detalhado!A9<=$C$11, Detalhado!J9, "") | I20: =IF(Detalhado!A9<=$C$11, Detalhado!M9, "") | J20: =IF(Detalhado!A9<=$C$11, Detalhado!N9, "")
B21: =IF(Detalhado!A10<=$C$11, Detalhado!A10, "") | C21: =IF(Detalhado!A10<=$C$11, Detalhado!C10, "") | D21: =IF(Detalhado!A10<=$C$11, Detalhado!D10, "") | E21: =IF(Detalhado!A10<=$C$11, Detalhado!E10, "") | F21: =IF(Detalhado!A10<=$C$11, Detalhado!G10, "") | G21: =IF(Detalhado!A10<=$C$11, Detalhado!H10, "") | H21: =IF(Detalhado!A10<=$C$11, Detalhado!J10, "") | I21: =IF(Detalhado!A10<=$C$11, Detalhado!M10, "") | J21: =IF(Detalhado!A10<=$C$11, Detalhado!N10, "")
B22: =IF(Detalhado!A11<=$C$11, Detalhado!A11, "") | C22: =IF(Detalhado!A11<=$C$11, Detalhado!C11, "") | D22: =IF(Detalhado!A11<=$C$11, Detalhado!D11, "") | E22: =IF(Detalhado!A11<=$C$11, Detalhado!E11, "") | F22: =IF(Detalhado!A11<=$C$11, Detalhado!G11, "") | G22: =IF(Detalhado!A11<=$C$11, Detalhado!H11, "") | H22: =IF(Detalhado!A11<=$C$11, Detalhado!J11, "") | I22: =IF(Detalhado!A11<=$C$11, Detalhado!M11, "") | J22: =IF(Detalhado!A11<=$C$11, Detalhado!N11, "")
B23: =IF(Detalhado!A12<=$C$11, Detalhado!A12, "") | C23: =IF(Detalhado!A12<=$C$11, Detalhado!C12, "") | D23: =IF(Detalhado!A12<=$C$11, Detalhado!D12, "") | E23: =IF(Detalhado!A12<=$C$11, Detalhado!E12, "") | F23: =IF(Detalhado!A12<=$C$11, Detalhado!G12, "") | G23: =IF(Detalhado!A12<=$C$11, Detalhado!H12, "") | H23: =IF(Detalhado!A12<=$C$11, Detalhado!J12, "") | I23: =IF(Detalhado!A12<=$C$11, Detalhado!M12, "") | J23: =IF(Detalhado!A12<=$C$11, Detalhado!N12, "")
B24: =IF(Detalhado!A13<=$C$11, Detalhado!A13, "") | C24: =IF(Detalhado!A13<=$C$11, Detalhado!C13, "") | D24: =IF(Detalhado!A13<=$C$11, Detalhado!D13, "") | E24: =IF(Detalhado!A13<=$C$11, Detalhado!E13, "") | F24: =IF(Detalhado!A13<=$C$11, Detalhado!G13, "") | G24: =IF(Detalhado!A13<=$C$11, Detalhado!H13, "") | H24: =IF(Detalhado!A13<=$C$11, Detalhado!J13, "") | I24: =IF(Detalhado!A13<=$C$11, Detalhado!M13, "") | J24: =IF(Detalhado!A13<=$C$11, Detalhado!N13, "")
B25: =IF(Detalhado!A14<=$C$11, Detalhado!A14, "") | C25: =IF(Detalhado!A14<=$C$11, Detalhado!C14, "") | D25: =IF(Detalhado!A14<=$C$11, Detalhado!D14, "") | E25: =IF(Detalhado!A14<=$C$11, Detalhado!E14, "") | F25: =IF(Detalhado!A14<=$C$11, Detalhado!G14, "") | G25: =IF(Detalhado!A14<=$C$11, Detalhado!H14, "") | H25: =IF(Detalhado!A14<=$C$11, Detalhado!J14, "") | I25: =IF(Detalhado!A14<=$C$11, Detalhado!M14, "") | J25: =IF(Detalhado!A14<=$C$11, Detalhado!N14, "")
B26: =IF(Detalhado!A15<=$C$11, Detalhado!A15, "") | C26: =IF(Detalhado!A15<=$C$11, Detalhado!C15, "") | D26: =IF(Detalhado!A15<=$C$11, Detalhado!D15, "") | E26: =IF(Detalhado!A15<=$C$11, Detalhado!E15, "") | F26: =IF(Detalhado!A15<=$C$11, Detalhado!G15, "") | G26: =IF(Detalhado!A15<=$C$11, Detalhado!H15, "") | H26: =IF(Detalhado!A15<=$C$11, Detalhado!J15, "") | I26: =IF(Detalhado!A15<=$C$11, Detalhado!M15, "") | J26: =IF(Detalhado!A15<=$C$11, Detalhado!N15, "")
... B32: =IF(Detalhado!A21<=$C$11, Detalhado!A21, "") | C32: =IF(Detalhado!A21<=$C$11, Detalhado!C21, "") | D32: =IF(Detalhado!A21<=$C$11, Detalhado!D21, "") | E32: =IF(Detalhado!A21<=$C$11, Detalhado!E21, "") | F32: =IF(Detalhado!A21<=$C$11, Detalhado!G21, "") | G32: =IF(Detalhado!A21<=$C$11, Detalhado!H21, "") | H32: =IF(Detalhado!A21<=$C$11, Detalhado!J21, "") | I32: =IF(Detalhado!A21<=$C$11, Detalhado!M21, "") | J32: =IF(Detalhado!A21<=$C$11, Detalhado!N21, "")
B33: TOTAL CONSOLIDADO | G33: =SUM(G15:G32) -> 658 | H33: =SUM(H15:H32) -> 14.41 | I33: =SUM(I15:I32) -> 20.27 | J33: =SUM(J15:J32) -> 623.32

Sheet Simulador Reverso
B2: SIMULADOR REVERSO DE ANTECIPAÇÃO
B3: Painel de cálculo reverso: defina o valor líquido desejado e obtenha o valor total a ser cobrado
B5: PARÂMETROS DA OPERAÇÃO | E5: VALOR TOTAL A COBRAR | G5: TOTAL DE DESCONTOS | I5: VALOR LÍQUIDO A RECEBER
B6: Data da Venda | C6: 46315 | E6: =Detalhado!U32 -> 658 | G6: =SUMPRODUCT((Detalhado!P4:P21<=C11)*(Detalhado!Z4:Z21 + Detalhado!AC4:AC21)) -> 34.68 | I6: =SUMPRODUCT((Detalhado!P4:P21<=C11)*(Detalhado!AD4:AD21)) -> 623.32
B7: Data de Recebimento | C7: 46316 | E7: =C11 & " parcelas de " & TEXT(Detalhado!U34, "R$ #,##0.00") -> 2 parcelas de R$ 329,00 | G7: =IF(E6>0, "MDR: " & TEXT(SUMPRODUCT((Detalhado!P4:P21<=C11)*(Detalhado!Z4:Z21)), "R$ #,##0.00") & " | Antec: " & TEXT(SUMPRODUCT((Detalhado!P4:P21<=C11)*(Detalhado!AC4:AC21)), "R$ #,##0.00"), "") -> MDR: R$ 14,41 | Antec: R$ 20,27 | I7: =IF(E6>0, "Recebimento líq. de " & ROUND((I6/E6)*100, 2) & "% do total", "") -> Recebimento líq. de 94,73% do total
B8: Taxa Antecipação (mês) | C8: 0.021
B9: Taxa Bandeira (MDR) | C9: 0.0219 | E9: VALOR DAS PARCELAS | G9: CUSTO EFETIVO TOTAL | I9: DATA RECEBIMENTO
B10: Valor Líquido Desejado | C10: 623.32 | E10: ="1ª " & TEXT(Detalhado!U33, "R$ #,##0.00") & " | Demais " & TEXT(Detalhado!U34, "R$ #,##0.00") -> 1ª R$ 329,00 | Demais R$ 329,00 | G10: =IF(E6>0, ROUND((G6/E6)*100, 2) & "%", "0.00%") -> 5,27% | I10: =C7 -> 46316
B11: Quantidade de Parcelas | C11: 2 | E11: 1ª parcela ajustada aos centavos | G11: ="Taxa MDR: " & TEXT(C9, "0.00%") & " | Antecipação: " & TEXT(C8, "0.00%") -> Taxa MDR: 2,19% | Antecipação: 2,10% | I11: Liquidação antecipada integral em D+1
B13: DETALHAMENTO DO CRONOGRAMA DE PARCELAS
B14: Parcela | C14: Vencimento Original | D14: Data Recebimento | E14: Dias Antec. | F14: Taxa Antec. | G14: Valor Bruto | H14: Desconto MDR | I14: Desconto Antec. | J14: Valor Líquido
B15: =IF(Detalhado!P4<=$C$11, Detalhado!P4, "") -> 1 | C15: =IF(Detalhado!P4<=$C$11, Detalhado!R4, "") -> 46345 | D15: =IF(Detalhado!P4<=$C$11, Detalhado!S4, "") -> 46316 | E15: =IF(Detalhado!P4<=$C$11, Detalhado!T4, "") -> 29 | F15: =IF(Detalhado!P4<=$C$11, Detalhado!V4, "") -> 0.0203 | G15: =IF(Detalhado!P4<=$C$11, Detalhado!X4, "") -> 329 | H15: =IF(Detalhado!P4<=$C$11, Detalhado!Z4, "") -> 7.21 | I15: =IF(Detalhado!P4<=$C$11, Detalhado!AC4, "") -> 6.53 | J15: =IF(Detalhado!P4<=$C$11, Detalhado!AD4, "") -> 315.26
B16: =IF(Detalhado!P5<=$C$11, Detalhado!P5, "") -> 2 | C16: =IF(Detalhado!P5<=$C$11, Detalhado!R5, "") -> 46377 | D16: =IF(Detalhado!P5<=$C$11, Detalhado!S5, "") -> 46316 | E16: =IF(Detalhado!P5<=$C$11, Detalhado!T5, "") -> 61 | F16: =IF(Detalhado!P5<=$C$11, Detalhado!V5, "") -> 0.0427 | G16: =IF(Detalhado!P5<=$C$11, Detalhado!X5, "") -> 329 | H16: =IF(Detalhado!P5<=$C$11, Detalhado!Z5, "") -> 7.2 | I16: =IF(Detalhado!P5<=$C$11, Detalhado!AC5, "") -> 13.74 | J16: =IF(Detalhado!P5<=$C$11, Detalhado!AD5, "") -> 308.06
B17: =IF(Detalhado!P6<=$C$11, Detalhado!P6, "") | C17: =IF(Detalhado!P6<=$C$11, Detalhado!R6, "") | D17: =IF(Detalhado!P6<=$C$11, Detalhado!S6, "") | E17: =IF(Detalhado!P6<=$C$11, Detalhado!T6, "") | F17: =IF(Detalhado!P6<=$C$11, Detalhado!V6, "") | G17: =IF(Detalhado!P6<=$C$11, Detalhado!X6, "") | H17: =IF(Detalhado!P6<=$C$11, Detalhado!Z6, "") | I17: =IF(Detalhado!P6<=$C$11, Detalhado!AC6, "") | J17: =IF(Detalhado!P6<=$C$11, Detalhado!AD6, "")
B18: =IF(Detalhado!P7<=$C$11, Detalhado!P7, "") | C18: =IF(Detalhado!P7<=$C$11, Detalhado!R7, "") | D18: =IF(Detalhado!P7<=$C$11, Detalhado!S7, "") | E18: =IF(Detalhado!P7<=$C$11, Detalhado!T7, "") | F18: =IF(Detalhado!P7<=$C$11, Detalhado!V7, "") | G18: =IF(Detalhado!P7<=$C$11, Detalhado!X7, "") | H18: =IF(Detalhado!P7<=$C$11, Detalhado!Z7, "") | I18: =IF(Detalhado!P7<=$C$11, Detalhado!AC7, "") | J18: =IF(Detalhado!P7<=$C$11, Detalhado!AD7, "")
B19: =IF(Detalhado!P8<=$C$11, Detalhado!P8, "") | C19: =IF(Detalhado!P8<=$C$11, Detalhado!R8, "") | D19: =IF(Detalhado!P8<=$C$11, Detalhado!S8, "") | E19: =IF(Detalhado!P8<=$C$11, Detalhado!T8, "") | F19: =IF(Detalhado!P8<=$C$11, Detalhado!V8, "") | G19: =IF(Detalhado!P8<=$C$11, Detalhado!X8, "") | H19: =IF(Detalhado!P8<=$C$11, Detalhado!Z8, "") | I19: =IF(Detalhado!P8<=$C$11, Detalhado!AC8, "") | J19: =IF(Detalhado!P8<=$C$11, Detalhado!AD8, "")
B20: =IF(Detalhado!P9<=$C$11, Detalhado!P9, "") | C20: =IF(Detalhado!P9<=$C$11, Detalhado!R9, "") | D20: =IF(Detalhado!P9<=$C$11, Detalhado!S9, "") | E20: =IF(Detalhado!P9<=$C$11, Detalhado!T9, "") | F20: =IF(Detalhado!P9<=$C$11, Detalhado!V9, "") | G20: =IF(Detalhado!P9<=$C$11, Detalhado!X9, "") | H20: =IF(Detalhado!P9<=$C$11, Detalhado!Z9, "") | I20: =IF(Detalhado!P9<=$C$11, Detalhado!AC9, "") | J20: =IF(Detalhado!P9<=$C$11, Detalhado!AD9, "")
B21: =IF(Detalhado!P10<=$C$11, Detalhado!P10, "") | C21: =IF(Detalhado!P10<=$C$11, Detalhado!R10, "") | D21: =IF(Detalhado!P10<=$C$11, Detalhado!S10, "") | E21: =IF(Detalhado!P10<=$C$11, Detalhado!T10, "") | F21: =IF(Detalhado!P10<=$C$11, Detalhado!V10, "") | G21: =IF(Detalhado!P10<=$C$11, Detalhado!X10, "") | H21: =IF(Detalhado!P10<=$C$11, Detalhado!Z10, "") | I21: =IF(Detalhado!P10<=$C$11, Detalhado!AC10, "") | J21: =IF(Detalhado!P10<=$C$11, Detalhado!AD10, "")
B22: =IF(Detalhado!P11<=$C$11, Detalhado!P11, "") | C22: =IF(Detalhado!P11<=$C$11, Detalhado!R11, "") | D22: =IF(Detalhado!P11<=$C$11, Detalhado!S11, "") | E22: =IF(Detalhado!P11<=$C$11, Detalhado!T11, "") | F22: =IF(Detalhado!P11<=$C$11, Detalhado!V11, "") | G22: =IF(Detalhado!P11<=$C$11, Detalhado!X11, "") | H22: =IF(Detalhado!P11<=$C$11, Detalhado!Z11, "") | I22: =IF(Detalhado!P11<=$C$11, Detalhado!AC11, "") | J22: =IF(Detalhado!P11<=$C$11, Detalhado!AD11, "")
B23: =IF(Detalhado!P12<=$C$11, Detalhado!P12, "") | C23: =IF(Detalhado!P12<=$C$11, Detalhado!R12, "") | D23: =IF(Detalhado!P12<=$C$11, Detalhado!S12, "") | E23: =IF(Detalhado!P12<=$C$11, Detalhado!T12, "") | F23: =IF(Detalhado!P12<=$C$11, Detalhado!V12, "") | G23: =IF(Detalhado!P12<=$C$11, Detalhado!X12, "") | H23: =IF(Detalhado!P12<=$C$11, Detalhado!Z12, "") | I23: =IF(Detalhado!P12<=$C$11, Detalhado!AC12, "") | J23: =IF(Detalhado!P12<=$C$11, Detalhado!AD12, "")
B24: =IF(Detalhado!P13<=$C$11, Detalhado!P13, "") | C24: =IF(Detalhado!P13<=$C$11, Detalhado!R13, "") | D24: =IF(Detalhado!P13<=$C$11, Detalhado!S13, "") | E24: =IF(Detalhado!P13<=$C$11, Detalhado!T13, "") | F24: =IF(Detalhado!P13<=$C$11, Detalhado!V13, "") | G24: =IF(Detalhado!P13<=$C$11, Detalhado!X13, "") | H24: =IF(Detalhado!P13<=$C$11, Detalhado!Z13, "") | I24: =IF(Detalhado!P13<=$C$11, Detalhado!AC13, "") | J24: =IF(Detalhado!P13<=$C$11, Detalhado!AD13, "")
B25: =IF(Detalhado!P14<=$C$11, Detalhado!P14, "") | C25: =IF(Detalhado!P14<=$C$11, Detalhado!R14, "") | D25: =IF(Detalhado!P14<=$C$11, Detalhado!S14, "") | E25: =IF(Detalhado!P14<=$C$11, Detalhado!T14, "") | F25: =IF(Detalhado!P14<=$C$11, Detalhado!V14, "") | G25: =IF(Detalhado!P14<=$C$11, Detalhado!X14, "") | H25: =IF(Detalhado!P14<=$C$11, Detalhado!Z14, "") | I25: =IF(Detalhado!P14<=$C$11, Detalhado!AC14, "") | J25: =IF(Detalhado!P14<=$C$11, Detalhado!AD14, "")
B26: =IF(Detalhado!P15<=$C$11, Detalhado!P15, "") | C26: =IF(Detalhado!P15<=$C$11, Detalhado!R15, "") | D26: =IF(Detalhado!P15<=$C$11, Detalhado!S15, "") | E26: =IF(Detalhado!P15<=$C$11, Detalhado!T15, "") | F26: =IF(Detalhado!P15<=$C$11, Detalhado!V15, "") | G26: =IF(Detalhado!P15<=$C$11, Detalhado!X15, "") | H26: =IF(Detalhado!P15<=$C$11, Detalhado!Z15, "") | I26: =IF(Detalhado!P15<=$C$11, Detalhado!AC15, "") | J26: =IF(Detalhado!P15<=$C$11, Detalhado!AD15, "")
... B32: =IF(Detalhado!P21<=$C$11, Detalhado!P21, "") | C32: =IF(Detalhado!P21<=$C$11, Detalhado!R21, "") | D32: =IF(Detalhado!P21<=$C$11, Detalhado!S21, "") | E32: =IF(Detalhado!P21<=$C$11, Detalhado!T21, "") | F32: =IF(Detalhado!P21<=$C$11, Detalhado!V21, "") | G32: =IF(Detalhado!P21<=$C$11, Detalhado!X21, "") | H32: =IF(Detalhado!P21<=$C$11, Detalhado!Z21, "") | I32: =IF(Detalhado!P21<=$C$11, Detalhado!AC21, "") | J32: =IF(Detalhado!P21<=$C$11, Detalhado!AD21, "")
B33: TOTAL CONSOLIDADO | G33: =SUM(G15:G32) -> 658 | H33: =SUM(H15:H32) -> 14.41 | I33: =SUM(I15:I32) -> 20.27 | J33: =SUM(J15:J32) -> 623.32

Sheet Detalhado
A2: Calculo da antecipação | P2: Cálculo da Antecipação Reversa (Líquido para Bruto)
A3: parcela | B3: data venda | C3: data pagamento | D3: data recebimento | E3: dias antecipados | F3: antecipação | G3: Antec. dia | H3: Bruto.parcela | I3: taxa (mdr) | J3: desc. taxa | K3: vl. sem taxa | L3: antecipação | M3: desc. ant | N3: liq. parcela | P3: parcela | Q3: data venda | R3: data pagamento | S3: data recebimento | T3: dias antecipados | U3: antecipação | V3: Antec. dia | W3: fator líq | X3: Bruto.parcela | Y3: taxa (mdr) | Z3: desc. taxa | AA3: vl. sem taxa | AB3: antecipação | AC3: desc. ant | AD3: liq. parcela
A4: 1 | B4: =F25 -> 46315 | C4: =WORKDAY(B4 + (A4 * 30) - 1, 1) -> 46345 | D4: =F26 -> 46316 | E4: =C4-D4 -> 29 | F4: =F27 -> 0.021 | G4: =ROUNDDOWN((F4/30)*E4, 4) -> 0.0203 | H4: =F31 -> 329 | I4: =F28 -> 0.0219 | J4: =ROUND(F$29*F$28, 2) - ((F$30-1) * ROUNDDOWN(F$32*F$28, 2)) -> 7.21 | K4: =H4-J4 -> 321.79 | L4: =G4 -> 0.0203 | M4: =ROUND(L4*K4, 2) -> 6.53 | N4: =K4-M4 -> 315.26 | P4: 1 | Q4: ='Simulador Reverso'!$C$6 -> 46315 | R4: =WORKDAY(Q4 + (P4 * 30) - 1, 1) -> 46345 | S4: ='Simulador Reverso'!$C$7 -> 46316 | T4: =R4-S4 -> 29 | U4: ='Simulador Reverso'!$C$8 -> 0.021 | V4: =ROUNDDOWN((U4/30)*T4, 4) -> 0.0203 | W4: =(1 - 'Simulador Reverso'!$C$9) * (1 - V4) -> 0.95824457 | X4: =U$33 -> 329 | Y4: ='Simulador Reverso'!$C$9 -> 0.0219 | Z4: =ROUND(U$32*Y4, 2) - ((U$30-1) * ROUNDDOWN(U$34*Y4, 2)) -> 7.21 | AA4: =X4-Z4 -> 321.79 | AB4: =V4 -> 0.0203 | AC4: =ROUND(AB4*AA4, 2) -> 6.53 | AD4: =AA4-AC4 -> 315.26
A5: 2 | B5: =B4 -> 46315 | C5: =WORKDAY(B5 + (A5 * 30) - 1, 1) -> 46377 | D5: =D4 -> 46316 | E5: =C5-D5 -> 61 | F5: =F4 -> 0.021 | G5: =ROUNDDOWN((F5/30)*E5, 4) -> 0.0427 | H5: =F32 -> 329 | I5: =F28 -> 0.0219 | J5: =ROUNDDOWN(H5*I5, 2) -> 7.2 | K5: =H5-J5 -> 321.8 | L5: =G5 -> 0.0427 | M5: =ROUND(L5*K5, 2) -> 13.74 | N5: =K5-M5 -> 308.06 | P5: 2 | Q5: =Q4 -> 46315 | R5: =WORKDAY(Q5 + (P5 * 30) - 1, 1) -> 46377 | S5: =S4 -> 46316 | T5: =R5-S5 -> 61 | U5: =U4 -> 0.021 | V5: =ROUNDDOWN((U5/30)*T5, 4) -> 0.0427 | W5: =(1 - 'Simulador Reverso'!$C$9) * (1 - V5) -> 0.93633513 | X5: =U$34 -> 329 | Y5: =Y4 -> 0.0219 | Z5: =ROUNDDOWN(X5*Y5, 2) -> 7.2 | AA5: =X5-Z5 -> 321.8 | AB5: =V5 -> 0.0427 | AC5: =ROUND(AB5*AA5, 2) -> 13.74 | AD5: =AA5-AC5 -> 308.06
A6: 3 | B6: =B5 -> 46315 | C6: =WORKDAY(B6 + (A6 * 30) - 1, 1) -> 46405 | D6: =D5 -> 46316 | E6: =C6-D6 -> 89 | F6: =F4 -> 0.021 | G6: =ROUNDDOWN((F6/30)*E6, 4) -> 0.0623 | H6: =F32 -> 329 | I6: =F28 -> 0.0219 | J6: =ROUNDDOWN(H6*I6, 2) -> 7.2 | K6: =H6-J6 -> 321.8 | L6: =G6 -> 0.0623 | M6: =ROUND(L6*K6, 2) -> 20.05 | N6: =K6-M6 -> 301.75 | P6: 3 | Q6: =Q4 -> 46315 | R6: =WORKDAY(Q6 + (P6 * 30) - 1, 1) -> 46405 | S6: =S4 -> 46316 | T6: =R6-S6 -> 89 | U6: =U4 -> 0.021 | V6: =ROUNDDOWN((U6/30)*T6, 4) -> 0.0623 | W6: =(1 - 'Simulador Reverso'!$C$9) * (1 - V6) -> 0.91716437 | X6: =U$34 -> 329 | Y6: =Y4 -> 0.0219 | Z6: =ROUNDDOWN(X6*Y6, 2) -> 7.2 | AA6: =X6-Z6 -> 321.8 | AB6: =V6 -> 0.0623 | AC6: =ROUND(AB6*AA6, 2) -> 20.05 | AD6: =AA6-AC6 -> 301.75
A7: 4 | B7: =B6 -> 46315 | C7: =WORKDAY(B7 + (A7 * 30) - 1, 1) -> 46435 | D7: =D6 -> 46316 | E7: =C7-D7 -> 119 | F7: =F4 -> 0.021 | G7: =ROUNDDOWN((F7/30)*E7, 4) -> 0.0833 | H7: =F32 -> 329 | I7: =F28 -> 0.0219 | J7: =ROUNDDOWN(H7*I7, 2) -> 7.2 | K7: =H7-J7 -> 321.8 | L7: =G7 -> 0.0833 | M7: =ROUND(L7*K7, 2) -> 26.81 | N7: =K7-M7 -> 294.99 | P7: 4 | Q7: =Q4 -> 46315 | R7: =WORKDAY(Q7 + (P7 * 30) - 1, 1) -> 46435 | S7: =S4 -> 46316 | T7: =R7-S7 -> 119 | U7: =U4 -> 0.021 | V7: =ROUNDDOWN((U7/30)*T7, 4) -> 0.0833 | W7: =(1 - 'Simulador Reverso'!$C$9) * (1 - V7) -> 0.89662427 | X7: =U$34 -> 329 | Y7: =Y4 -> 0.0219 | Z7: =ROUNDDOWN(X7*Y7, 2) -> 7.2 | AA7: =X7-Z7 -> 321.8 | AB7: =V7 -> 0.0833 | AC7: =ROUND(AB7*AA7, 2) -> 26.81 | AD7: =AA7-AC7 -> 294.99
A8: 5 | B8: =B7 -> 46315 | C8: =WORKDAY(B8 + (A8 * 30) - 1, 1) -> 46465 | D8: =D7 -> 46316 | E8: =C8-D8 -> 149 | F8: =F4 -> 0.021 | G8: =ROUNDDOWN((F8/30)*E8, 4) -> 0.1043 | H8: =F32 -> 329 | I8: =F28 -> 0.0219 | J8: =ROUNDDOWN(H8*I8, 2) -> 7.2 | K8: =H8-J8 -> 321.8 | L8: =G8 -> 0.1043 | M8: =ROUND(L8*K8, 2) -> 33.56 | N8: =K8-M8 -> 288.24 | P8: 5 | Q8: =Q4 -> 46315 | R8: =WORKDAY(Q8 + (P8 * 30) - 1, 1) -> 46465 | S8: =S4 -> 46316 | T8: =R8-S8 -> 149 | U8: =U4 -> 0.021 | V8: =ROUNDDOWN((U8/30)*T8, 4) -> 0.1043 | W8: =(1 - 'Simulador Reverso'!$C$9) * (1 - V8) -> 0.87608417 | X8: =U$34 -> 329 | Y8: =Y4 -> 0.0219 | Z8: =ROUNDDOWN(X8*Y8, 2) -> 7.2 | AA8: =X8-Z8 -> 321.8 | AB8: =V8 -> 0.1043 | AC8: =ROUND(AB8*AA8, 2) -> 33.56 | AD8: =AA8-AC8 -> 288.24
A9: 6 | B9: =B8 -> 46315 | C9: =WORKDAY(B9 + (A9 * 30) - 1, 1) -> 46496 | D9: =D8 -> 46316 | E9: =C9-D9 -> 180 | F9: =F4 -> 0.021 | G9: =ROUNDDOWN((F9/30)*E9, 4) -> 0.126 | H9: =F32 -> 329 | I9: =F28 -> 0.0219 | J9: =ROUNDDOWN(H9*I9, 2) -> 7.2 | K9: =H9-J9 -> 321.8 | L9: =G9 -> 0.126 | M9: =ROUND(L9*K9, 2) -> 40.55 | N9: =K9-M9 -> 281.25 | P9: 6 | Q9: =Q4 -> 46315 | R9: =WORKDAY(Q9 + (P9 * 30) - 1, 1) -> 46496 | S9: =S4 -> 46316 | T9: =R9-S9 -> 180 | U9: =U4 -> 0.021 | V9: =ROUNDDOWN((U9/30)*T9, 4) -> 0.126 | W9: =(1 - 'Simulador Reverso'!$C$9) * (1 - V9) -> 0.8548594 | X9: =U$34 -> 329 | Y9: =Y4 -> 0.0219 | Z9: =ROUNDDOWN(X9*Y9, 2) -> 7.2 | AA9: =X9-Z9 -> 321.8 | AB9: =V9 -> 0.126 | AC9: =ROUND(AB9*AA9, 2) -> 40.55 | AD9: =AA9-AC9 -> 281.25
A10: 7 | B10: =B9 -> 46315 | C10: =WORKDAY(B10 + (A10 * 30) - 1, 1) -> 46525 | D10: =D9 -> 46316 | E10: =C10-D10 -> 209 | F10: =F4 -> 0.021 | G10: =ROUNDDOWN((F10/30)*E10, 4) -> 0.1463 | H10: =F32 -> 329 | I10: =F28 -> 0.0219 | J10: =ROUNDDOWN(H10*I10, 2) -> 7.2 | K10: =H10-J10 -> 321.8 | L10: =G10 -> 0.1463 | M10: =ROUND(L10*K10, 2) -> 47.08 | N10: =K10-M10 -> 274.72 | P10: 7 | Q10: =Q4 -> 46315 | R10: =WORKDAY(Q10 + (P10 * 30) - 1, 1) -> 46525 | S10: =S4 -> 46316 | T10: =R10-S10 -> 209 | U10: =U4 -> 0.021 | V10: =ROUNDDOWN((U10/30)*T10, 4) -> 0.1463 | W10: =(1 - 'Simulador Reverso'!$C$9) * (1 - V10) -> 0.83500397 | X10: =U$34 -> 329 | Y10: =Y4 -> 0.0219 | Z10: =ROUNDDOWN(X10*Y10, 2) -> 7.2 | AA10: =X10-Z10 -> 321.8 | AB10: =V10 -> 0.1463 | AC10: =ROUND(AB10*AA10, 2) -> 47.08 | AD10: =AA10-AC10 -> 274.72
A11: 8 | B11: =B10 -> 46315 | C11: =WORKDAY(B11 + (A11 * 30) - 1, 1) -> 46555 | D11: =D10 -> 46316 | E11: =C11-D11 -> 239 | F11: =F4 -> 0.021 | G11: =ROUNDDOWN((F11/30)*E11, 4) -> 0.1673 | H11: =F32 -> 329 | I11: =F28 -> 0.0219 | J11: =ROUNDDOWN(H11*I11, 2) -> 7.2 | K11: =H11-J11 -> 321.8 | L11: =G11 -> 0.1673 | M11: =ROUND(L11*K11, 2) -> 53.84 | N11: =K11-M11 -> 267.96 | P11: 8 | Q11: =Q4 -> 46315 | R11: =WORKDAY(Q11 + (P11 * 30) - 1, 1) -> 46555 | S11: =S4 -> 46316 | T11: =R11-S11 -> 239 | U11: =U4 -> 0.021 | V11: =ROUNDDOWN((U11/30)*T11, 4) -> 0.1673 | W11: =(1 - 'Simulador Reverso'!$C$9) * (1 - V11) -> 0.81446387 | X11: =U$34 -> 329 | Y11: =Y4 -> 0.0219 | Z11: =ROUNDDOWN(X11*Y11, 2) -> 7.2 | AA11: =X11-Z11 -> 321.8 | AB11: =V11 -> 0.1673 | AC11: =ROUND(AB11*AA11, 2) -> 53.84 | AD11: =AA11-AC11 -> 267.96
A12: 9 | B12: =B11 -> 46315 | C12: =WORKDAY(B12 + (A12 * 30) - 1, 1) -> 46587 | D12: =D11 -> 46316 | E12: =C12-D12 -> 271 | F12: =F4 -> 0.021 | G12: =ROUNDDOWN((F12/30)*E12, 4) -> 0.1897 | H12: =F32 -> 329 | I12: =F28 -> 0.0219 | J12: =ROUNDDOWN(H12*I12, 2) -> 7.2 | K12: =H12-J12 -> 321.8 | L12: =G12 -> 0.1897 | M12: =ROUND(L12*K12, 2) -> 61.05 | N12: =K12-M12 -> 260.75 | P12: 9 | Q12: =Q4 -> 46315 | R12: =WORKDAY(Q12 + (P12 * 30) - 1, 1) -> 46587 | S12: =S4 -> 46316 | T12: =R12-S12 -> 271 | U12: =U4 -> 0.021 | V12: =ROUNDDOWN((U12/30)*T12, 4) -> 0.1897 | W12: =(1 - 'Simulador Reverso'!$C$9) * (1 - V12) -> 0.79255443 | X12: =U$34 -> 329 | Y12: =Y4 -> 0.0219 | Z12: =ROUNDDOWN(X12*Y12, 2) -> 7.2 | AA12: =X12-Z12 -> 321.8 | AB12: =V12 -> 0.1897 | AC12: =ROUND(AB12*AA12, 2) -> 61.05 | AD12: =AA12-AC12 -> 260.75
A13: 10 | B13: =B12 -> 46315 | C13: =WORKDAY(B13 + (A13 * 30) - 1, 1) -> 46615 | D13: =D12 -> 46316 | E13: =C13-D13 -> 299 | F13: =F4 -> 0.021 | G13: =ROUNDDOWN((F13/30)*E13, 4) -> 0.2093 | H13: =F32 -> 329 | I13: =F28 -> 0.0219 | J13: =ROUNDDOWN(H13*I13, 2) -> 7.2 | K13: =H13-J13 -> 321.8 | L13: =G13 -> 0.2093 | M13: =ROUND(L13*K13, 2) -> 67.35 | N13: =K13-M13 -> 254.45 | P13: 10 | Q13: =Q4 -> 46315 | R13: =WORKDAY(Q13 + (P13 * 30) - 1, 1) -> 46615 | S13: =S4 -> 46316 | T13: =R13-S13 -> 299 | U13: =U4 -> 0.021 | V13: =ROUNDDOWN((U13/30)*T13, 4) -> 0.2093 | W13: =(1 - 'Simulador Reverso'!$C$9) * (1 - V13) -> 0.77338367 | X13: =U$34 -> 329 | Y13: =Y4 -> 0.0219 | Z13: =ROUNDDOWN(X13*Y13, 2) -> 7.2 | AA13: =X13-Z13 -> 321.8 | AB13: =V13 -> 0.2093 | AC13: =ROUND(AB13*AA13, 2) -> 67.35 | AD13: =AA13-AC13 -> 254.45
A14: 11 | B14: =B13 -> 46315 | C14: =WORKDAY(B14 + (A14 * 30) - 1, 1) -> 46645 | D14: =D13 -> 46316 | E14: =C14-D14 -> 329 | F14: =F5 -> 0.021 | G14: =ROUNDDOWN((F14/30)*E14, 4) -> 0.2303 | H14: =F32 -> 329 | I14: =F28 -> 0.0219 | J14: =ROUNDDOWN(H14*I14, 2) -> 7.2 | K14: =H14-J14 -> 321.8 | L14: =G14 -> 0.2303 | M14: =ROUND(L14*K14, 2) -> 74.11 | N14: =K14-M14 -> 247.69 | P14: 11 | Q14: =Q4 -> 46315 | R14: =WORKDAY(Q14 + (P14 * 30) - 1, 1) -> 46645 | S14: =S4 -> 46316 | T14: =R14-S14 -> 329 | U14: =U4 -> 0.021 | V14: =ROUNDDOWN((U14/30)*T14, 4) -> 0.2303 | W14: =(1 - 'Simulador Reverso'!$C$9) * (1 - V14) -> 0.75284357 | X14: =U$34 -> 329 | Y14: =Y4 -> 0.0219 | Z14: =ROUNDDOWN(X14*Y14, 2) -> 7.2 | AA14: =X14-Z14 -> 321.8 | AB14: =V14 -> 0.2303 | AC14: =ROUND(AB14*AA14, 2) -> 74.11 | AD14: =AA14-AC14 -> 247.69
A15: 12 | B15: =B14 -> 46315 | C15: =WORKDAY(B15 + (A15 * 30) - 1, 1) -> 46675 | D15: =D14 -> 46316 | E15: =C15-D15 -> 359 | F15: =F6 -> 0.021 | G15: =ROUNDDOWN((F15/30)*E15, 4) -> 0.2513 | H15: =F32 -> 329 | I15: =F28 -> 0.0219 | J15: =ROUNDDOWN(H15*I15, 2) -> 7.2 | K15: =H15-J15 -> 321.8 | L15: =G15 -> 0.2513 | M15: =ROUND(L15*K15, 2) -> 80.87 | N15: =K15-M15 -> 240.93 | P15: 12 | Q15: =Q4 -> 46315 | R15: =WORKDAY(Q15 + (P15 * 30) - 1, 1) -> 46675 | S15: =S4 -> 46316 | T15: =R15-S15 -> 359 | U15: =U4 -> 0.021 | V15: =ROUNDDOWN((U15/30)*T15, 4) -> 0.2513 | W15: =(1 - 'Simulador Reverso'!$C$9) * (1 - V15) -> 0.73230347 | X15: =U$34 -> 329 | Y15: =Y4 -> 0.0219 | Z15: =ROUNDDOWN(X15*Y15, 2) -> 7.2 | AA15: =X15-Z15 -> 321.8 | AB15: =V15 -> 0.2513 | AC15: =ROUND(AB15*AA15, 2) -> 80.87 | AD15: =AA15-AC15 -> 240.93
A16: 13 | B16: =B15 -> 46315 | C16: =WORKDAY(B16 + (A16 * 30) - 1, 1) -> 46706 | D16: =D15 -> 46316 | E16: =C16-D16 -> 390 | F16: =F7 -> 0.021 | G16: =ROUNDDOWN((F16/30)*E16, 4) -> 0.273 | H16: =F32 -> 329 | I16: =F28 -> 0.0219 | J16: =ROUNDDOWN(H16*I16, 2) -> 7.2 | K16: =H16-J16 -> 321.8 | L16: =G16 -> 0.273 | M16: =ROUND(L16*K16, 2) -> 87.85 | N16: =K16-M16 -> 233.95 | P16: 13 | Q16: =Q4 -> 46315 | R16: =WORKDAY(Q16 + (P16 * 30) - 1, 1) -> 46706 | S16: =S4 -> 46316 | T16: =R16-S16 -> 390 | U16: =U4 -> 0.021 | V16: =ROUNDDOWN((U16/30)*T16, 4) -> 0.273 | W16: =(1 - 'Simulador Reverso'!$C$9) * (1 - V16) -> 0.7110787 | X16: =U$34 -> 329 | Y16: =Y4 -> 0.0219 | Z16: =ROUNDDOWN(X16*Y16, 2) -> 7.2 | AA16: =X16-Z16 -> 321.8 | AB16: =V16 -> 0.273 | AC16: =ROUND(AB16*AA16, 2) -> 87.85 | AD16: =AA16-AC16 -> 233.95
A17: 14 | B17: =B16 -> 46315 | C17: =WORKDAY(B17 + (A17 * 30) - 1, 1) -> 46735 | D17: =D16 -> 46316 | E17: =C17-D17 -> 419 | F17: =F8 -> 0.021 | G17: =ROUNDDOWN((F17/30)*E17, 4) -> 0.2933 | H17: =F32 -> 329 | I17: =F28 -> 0.0219 | J17: =ROUNDDOWN(H17*I17, 2) -> 7.2 | K17: =H17-J17 -> 321.8 | L17: =G17 -> 0.2933 | M17: =ROUND(L17*K17, 2) -> 94.38 | N17: =K17-M17 -> 227.42 | P17: 14 | Q17: =Q4 -> 46315 | R17: =WORKDAY(Q17 + (P17 * 30) - 1, 1) -> 46735 | S17: =S4 -> 46316 | T17: =R17-S17 -> 419 | U17: =U4 -> 0.021 | V17: =ROUNDDOWN((U17/30)*T17, 4) -> 0.2933 | W17: =(1 - 'Simulador Reverso'!$C$9) * (1 - V17) -> 0.69122327 | X17: =U$34 -> 329 | Y17: =Y4 -> 0.0219 | Z17: =ROUNDDOWN(X17*Y17, 2) -> 7.2 | AA17: =X17-Z17 -> 321.8 | AB17: =V17 -> 0.2933 | AC17: =ROUND(AB17*AA17, 2) -> 94.38 | AD17: =AA17-AC17 -> 227.42
A18: 15 | B18: =B17 -> 46315 | C18: =WORKDAY(B18 + (A18 * 30) - 1, 1) -> 46765 | D18: =D17 -> 46316 | E18: =C18-D18 -> 449 | F18: =F9 -> 0.021 | G18: =ROUNDDOWN((F18/30)*E18, 4) -> 0.3143 | H18: =F32 -> 329 | I18: =F28 -> 0.0219 | J18: =ROUNDDOWN(H18*I18, 2) -> 7.2 | K18: =H18-J18 -> 321.8 | L18: =G18 -> 0.3143 | M18: =ROUND(L18*K18, 2) -> 101.14 | N18: =K18-M18 -> 220.66 | P18: 15 | Q18: =Q4 -> 46315 | R18: =WORKDAY(Q18 + (P18 * 30) - 1, 1) -> 46765 | S18: =S4 -> 46316 | T18: =R18-S18 -> 449 | U18: =U4 -> 0.021 | V18: =ROUNDDOWN((U18/30)*T18, 4) -> 0.3143 | W18: =(1 - 'Simulador Reverso'!$C$9) * (1 - V18) -> 0.67068317 | X18: =U$34 -> 329 | Y18: =Y4 -> 0.0219 | Z18: =ROUNDDOWN(X18*Y18, 2) -> 7.2 | AA18: =X18-Z18 -> 321.8 | AB18: =V18 -> 0.3143 | AC18: =ROUND(AB18*AA18, 2) -> 101.14 | AD18: =AA18-AC18 -> 220.66
A19: 16 | B19: =B18 -> 46315 | C19: =WORKDAY(B19 + (A19 * 30) - 1, 1) -> 46797 | D19: =D18 -> 46316 | E19: =C19-D19 -> 481 | F19: =F10 -> 0.021 | G19: =ROUNDDOWN((F19/30)*E19, 4) -> 0.3367 | H19: =F32 -> 329 | I19: =F28 -> 0.0219 | J19: =ROUNDDOWN(H19*I19, 2) -> 7.2 | K19: =H19-J19 -> 321.8 | L19: =G19 -> 0.3367 | M19: =ROUND(L19*K19, 2) -> 108.35 | N19: =K19-M19 -> 213.45 | P19: 16 | Q19: =Q4 -> 46315 | R19: =WORKDAY(Q19 + (P19 * 30) - 1, 1) -> 46797 | S19: =S4 -> 46316 | T19: =R19-S19 -> 481 | U19: =U4 -> 0.021 | V19: =ROUNDDOWN((U19/30)*T19, 4) -> 0.3367 | W19: =(1 - 'Simulador Reverso'!$C$9) * (1 - V19) -> 0.64877373 | X19: =U$34 -> 329 | Y19: =Y4 -> 0.0219 | Z19: =ROUNDDOWN(X19*Y19, 2) -> 7.2 | AA19: =X19-Z19 -> 321.8 | AB19: =V19 -> 0.3367 | AC19: =ROUND(AB19*AA19, 2) -> 108.35 | AD19: =AA19-AC19 -> 213.45
A20: 17 | B20: =B19 -> 46315 | C20: =WORKDAY(B20 + (A20 * 30) - 1, 1) -> 46825 | D20: =D19 -> 46316 | E20: =C20-D20 -> 509 | F20: =F11 -> 0.021 | G20: =ROUNDDOWN((F20/30)*E20, 4) -> 0.3563 | H20: =F32 -> 329 | I20: =F28 -> 0.0219 | J20: =ROUNDDOWN(H20*I20, 2) -> 7.2 | K20: =H20-J20 -> 321.8 | L20: =G20 -> 0.3563 | M20: =ROUND(L20*K20, 2) -> 114.66 | N20: =K20-M20 -> 207.14 | P20: 17 | Q20: =Q4 -> 46315 | R20: =WORKDAY(Q20 + (P20 * 30) - 1, 1) -> 46825 | S20: =S4 -> 46316 | T20: =R20-S20 -> 509 | U20: =U4 -> 0.021 | V20: =ROUNDDOWN((U20/30)*T20, 4) -> 0.3563 | W20: =(1 - 'Simulador Reverso'!$C$9) * (1 - V20) -> 0.62960297 | X20: =U$34 -> 329 | Y20: =Y4 -> 0.0219 | Z20: =ROUNDDOWN(X20*Y20, 2) -> 7.2 | AA20: =X20-Z20 -> 321.8 | AB20: =V20 -> 0.3563 | AC20: =ROUND(AB20*AA20, 2) -> 114.66 | AD20: =AA20-AC20 -> 207.14
A21: 18 | B21: =B20 -> 46315 | C21: =WORKDAY(B21 + (A21 * 30) - 1, 1) -> 46855 | D21: =D20 -> 46316 | E21: =C21-D21 -> 539 | F21: =F12 -> 0.021 | G21: =ROUNDDOWN((F21/30)*E21, 4) -> 0.3773 | H21: =F32 -> 329 | I21: =F28 -> 0.0219 | J21: =ROUNDDOWN(H21*I21, 2) -> 7.2 | K21: =H21-J21 -> 321.8 | L21: =G21 -> 0.3773 | M21: =ROUND(L21*K21, 2) -> 121.42 | N21: =K21-M21 -> 200.38 | P21: 18 | Q21: =Q4 -> 46315 | R21: =WORKDAY(Q21 + (P21 * 30) - 1, 1) -> 46855 | S21: =S4 -> 46316 | T21: =R21-S21 -> 539 | U21: =U4 -> 0.021 | V21: =ROUNDDOWN((U21/30)*T21, 4) -> 0.3773 | W21: =(1 - 'Simulador Reverso'!$C$9) * (1 - V21) -> 0.60906287 | X21: =U$34 -> 329 | Y21: =Y4 -> 0.0219 | Z21: =ROUNDDOWN(X21*Y21, 2) -> 7.2 | AA21: =X21-Z21 -> 321.8 | AB21: =V21 -> 0.3773 | AC21: =ROUND(AB21*AA21, 2) -> 121.42 | AD21: =AA21-AC21 -> 200.38
E25: Data da venda: | F25: =Simulador!C6 -> 46315 | T25: Data da venda: | U25: ='Simulador Reverso'!C6 -> 46315
E26: Data recebimento: | F26: =Simulador!C7 -> 46316 | T26: Data recebimento: | U26: ='Simulador Reverso'!C7 -> 46316
E27: taxa antecipação | F27: =Simulador!C8 -> 0.021 | T27: taxa antecipação | U27: ='Simulador Reverso'!C8 -> 0.021
E28: taxa bandeira | F28: =Simulador!C9 -> 0.0219 | T28: taxa bandeira | U28: ='Simulador Reverso'!C9 -> 0.0219
E29: valor: | F29: =Simulador!C10 -> 658 | T29: valor líquido desejado: | U29: ='Simulador Reverso'!C10 -> 623.32
E30: parcelas: | F30: =Simulador!C11 -> 2 | T30: parcelas: | U30: ='Simulador Reverso'!C11 -> 2
E31: valor parcela 1: | F31: =ROUND(F29 - (F30 - 1) * F32, 2) -> 329 | T31: fator líquido médio: | U31: =IF(U30>0, SUMPRODUCT((P4:P21<=U30)*W4:W21)/U30, 1) -> 0.94728985
E32: valor demais parcelas: | F32: =ROUNDDOWN(F29 * ROUND(1/F30, 4), 2) -> 329 | T32: valor bruto calculado: | U32: =IF(U31>0, ROUND(U29/U31, 2), 0) -> 658
T33: valor parcela 1: | U33: =ROUND(U32 - (U30 - 1) * U34, 2) -> 329
T34: valor demais parcelas: | U34: =ROUNDDOWN(U32 * ROUND(1/U30, 4), 2) -> 329
